phonkd_bot/__init__.py
phonkd_bot/api_handler.py
phonkd_bot/logger.py
phonkd_bot/cogs/on_message.py
phonkd_bot/cogs/on_ready.py
phonkd_bot/cogs/__pycache__/on_message.cpython-311.pyc
phonkd_bot/cogs/__pycache__/on_ready.cpython-311.pyc
phonkd_bot-1.0.2.dist-info/LICENSE
phonkd_bot-1.0.2.dist-info/METADATA
phonkd_bot-1.0.2.dist-info/WHEEL
phonkd_bot-1.0.2.dist-info/top_level.txt
phonkd_bot-1.0.2.dist-info/RECORD
