Metadata-Version: 2.1
Name: phonkd-bot
Version: 1.0.2
Summary: A framework that makes discord bot programming easy
Author: Phonki
Author-email: <phonkibusiness@gmail.com>
Keywords: python,discord
Classifier: Development Status :: 5 - Production/Stable
Classifier: Intended Audience :: Developers
Classifier: Programming Language :: Python :: 3
Classifier: Operating System :: Unix
Classifier: Operating System :: MacOS
Classifier: Operating System :: Microsoft :: Windows
License-File: LICENSE
Requires-Dist: discord
Requires-Dist: asyncio
